vaskify/__init__.py
vaskify/__main__.py
vaskify/createdata.py
vaskify/detect.py
vaskify/py.typed
ssb_vaskify-0.0.5.dist-info/METADATA
ssb_vaskify-0.0.5.dist-info/WHEEL
ssb_vaskify-0.0.5.dist-info/entry_points.txt
ssb_vaskify-0.0.5.dist-info/licenses/LICENSE
ssb_vaskify-0.0.5.dist-info/RECORD
