Metadata-Version: 2.4
Name: ssb-vaskify
Version: 0.0.5
Summary: Functions for control and editing of data in official statistics.
License-Expression: MIT
License-File: LICENSE
Author: Susie Jentoft
Author-email: susie.jentoft@ssb.no
Requires-Python: >=3.10,<4.0
Classifier: Development Status :: 3 - Alpha
Classifier: Programming Language :: Python :: 3
Classifier: Programming Language :: Python :: 3.10
Classifier: Programming Language :: Python :: 3.11
Classifier: Programming Language :: Python :: 3.12
Classifier: Programming Language :: Python :: 3.13
Classifier: Programming Language :: Python :: 3.14
Requires-Dist: click (>=8.0.1)
Requires-Dist: numpy (>=2.1.3)
Requires-Dist: pandas (>=2.2.3)
Requires-Dist: pandas-stubs (>=2.2.3.241126)
Project-URL: Documentation, https://statisticsnorway.github.io/ssb-vaskify
Project-URL: Homepage, https://github.com/statisticsnorway/ssb-vaskify
Project-URL: Repository, https://github.com/statisticsnorway/ssb-vaskify
